gbdx_buffet/__init__.py
gbdx_buffet/pipeline.py
gbdx_buffet-2018.4.24.0.dist-info/DESCRIPTION.rst
gbdx_buffet-2018.4.24.0.dist-info/METADATA
gbdx_buffet-2018.4.24.0.dist-info/RECORD
gbdx_buffet-2018.4.24.0.dist-info/WHEEL
gbdx_buffet-2018.4.24.0.dist-info/entry_points.txt
gbdx_buffet-2018.4.24.0.dist-info/metadata.json
gbdx_buffet-2018.4.24.0.dist-info/top_level.txt
